aeoncloud/__init__.py
aeoncloud/cloud/__init__.py
aeoncloud/cloud/async_http_client.py
aeoncloud/cloud/async_http_cloud_adapter.py
aeoncloud/cloud/cloud_adapter.py
aeoncloud/cloud/http_client.py
aeoncloud/cloud/http_cloud_adapter.py
aeoncloud/exceptions/__init__.py
aeoncloud/exceptions/aeon_cloud_error.py
aeoncloud/exceptions/aeon_session_error.py
aeoncloud/exceptions/not_found_error.py
aeoncloud/sessions/__init__.py
aeoncloud/sessions/async_http_client.py
aeoncloud/sessions/async_http_session_adapter.py
aeoncloud/sessions/http_client.py
aeoncloud/sessions/http_session_adapter.py
aeoncloud/sessions/http_session_factory_adapter.py
aeoncloud/sessions/session_adapter.py
aeoncloud/sessions/session_factory_adapter.py
aeoncloud-0.1.4.dist-info/DESCRIPTION.rst
aeoncloud-0.1.4.dist-info/METADATA
aeoncloud-0.1.4.dist-info/RECORD
aeoncloud-0.1.4.dist-info/WHEEL
aeoncloud-0.1.4.dist-info/metadata.json
aeoncloud-0.1.4.dist-info/top_level.txt
tests/__init__.py
tests/cloud/__init__.py
tests/cloud/test_async_http_client.py
tests/cloud/test_async_http_cloud_adapter.py
tests/cloud/test_http_client.py
tests/cloud/test_http_cloud_adapter.py
tests/utils/__init__.py
tests/utils/equals.py
