Metadata-Version: 2.0
Name: aeoncloud
Version: 0.1.4
Summary: Aeon Cloud Python
Home-page: https://ultigit.ultimatesoftware.com/projects/VT/repos/aeon-cloud-python-client/browse
Author: Genesis
Author-email: dev-genesis@ultimatesoftware.com
License: UNKNOWN
Platform: UNKNOWN
Classifier: Programming Language :: Python :: 3
Classifier: Operating System :: OS Independent
Requires-Dist: requests
Requires-Dist: aiohttp
